<?xml version="1.0" encoding="UTF-8"?>
<v8msg:Message xmlns:v8msg="http://v8.1c.ru/messages">
	<v8msg:Header>
		<v8msg:ExchangePlan>Мобильные</v8msg:ExchangePlan>
		<v8msg:To>МПТ</v8msg:To>
		<v8msg:From>ЦО</v8msg:From>
		<v8msg:MessageNo>2</v8msg:MessageNo>
		<v8msg:ReceivedNo>0</v8msg:ReceivedNo>
	</v8msg:Header>
	<v8msg:Body>
		<CatalogObject.Товары>
			<Ref>9b2782c4-5b90-11ed-9bff-841c095bda83</Ref>
			<IsFolder>true</IsFolder>
			<DeletionMark>false</DeletionMark>
			<Parent>00000000-0000-0000-0000-000000000000</Parent>
			<Code>000000001</Code>
			<Description>Овощи</Description>
		</CatalogObject.Товары>
		<CatalogObject.Товары>
			<Ref>9b2782c5-5b90-11ed-9bff-841c095bda83</Ref>
			<IsFolder>true</IsFolder>
			<DeletionMark>false</DeletionMark>
			<Parent>00000000-0000-0000-0000-000000000000</Parent>
			<Code>000000002</Code>
			<Description>Фрукты</Description>
		</CatalogObject.Товары>
		<CatalogObject.Товары>
			<Ref>9b2782c6-5b90-11ed-9bff-841c095bda83</Ref>
			<IsFolder>false</IsFolder>
			<DeletionMark>false</DeletionMark>
			<Parent>9b2782c5-5b90-11ed-9bff-841c095bda83</Parent>
			<Code>000000003</Code>
			<Description>Яблоко</Description>
			<Артикул>001</Артикул>
			<Описание/>
		</CatalogObject.Товары>
		<CatalogObject.Товары>
			<Ref>9b2782c7-5b90-11ed-9bff-841c095bda83</Ref>
			<IsFolder>false</IsFolder>
			<DeletionMark>false</DeletionMark>
			<Parent>9b2782c5-5b90-11ed-9bff-841c095bda83</Parent>
			<Code>000000004</Code>
			<Description>Груша</Description>
			<Артикул>002</Артикул>
			<Описание/>
		</CatalogObject.Товары>
		<CatalogObject.Товары>
			<Ref>9b2782c8-5b90-11ed-9bff-841c095bda83</Ref>
			<IsFolder>false</IsFolder>
			<DeletionMark>false</DeletionMark>
			<Parent>9b2782c5-5b90-11ed-9bff-841c095bda83</Parent>
			<Code>000000005</Code>
			<Description>Мандарин</Description>
			<Артикул>003</Артикул>
			<Описание/>
		</CatalogObject.Товары>
		<CatalogObject.Товары>
			<Ref>9b2782c9-5b90-11ed-9bff-841c095bda83</Ref>
			<IsFolder>false</IsFolder>
			<DeletionMark>false</DeletionMark>
			<Parent>9b2782c4-5b90-11ed-9bff-841c095bda83</Parent>
			<Code>000000006</Code>
			<Description>Помидор</Description>
			<Артикул>004</Артикул>
			<Описание/>
		</CatalogObject.Товары>
		<CatalogObject.Товары>
			<Ref>9b2782ca-5b90-11ed-9bff-841c095bda83</Ref>
			<IsFolder>false</IsFolder>
			<DeletionMark>false</DeletionMark>
			<Parent>9b2782c4-5b90-11ed-9bff-841c095bda83</Parent>
			<Code>000000007</Code>
			<Description>Капуста</Description>
			<Артикул>005</Артикул>
			<Описание/>
		</CatalogObject.Товары>
		<CatalogObject.Товары>
			<Ref>9b2782cb-5b90-11ed-9bff-841c095bda83</Ref>
			<IsFolder>false</IsFolder>
			<DeletionMark>false</DeletionMark>
			<Parent>9b2782c4-5b90-11ed-9bff-841c095bda83</Parent>
			<Code>000000008</Code>
			<Description>Свекла</Description>
			<Артикул>006</Артикул>
			<Описание/>
		</CatalogObject.Товары>
		<ObjectDeletion xmlns="http://v8.1c.ru/data">
			<d4p1:Ref xmlns="" xmlns:d4p1="http://v8.1c.ru/data" xmlns:xsi="http://www.w3.org/2001/XMLSchema-instance" xsi:type="DocumentRef.ОбслуживаниеЗаказов">9b2782de-5b90-11ed-9bff-841c095bda83</d4p1:Ref>
		</ObjectDeletion>
		<ObjectDeletion xmlns="http://v8.1c.ru/data">
			<d4p1:Ref xmlns="" xmlns:d4p1="http://v8.1c.ru/data" xmlns:xsi="http://www.w3.org/2001/XMLSchema-instance" xsi:type="DocumentRef.ОбслуживаниеЗаказов">9b2782df-5b90-11ed-9bff-841c095bda83</d4p1:Ref>
		</ObjectDeletion>
		<CatalogObject.Клиенты>
			<Ref>9b2782cc-5b90-11ed-9bff-841c095bda83</Ref>
			<DeletionMark>false</DeletionMark>
			<Code>000000001</Code>
			<Description>Урявин Александр Сергеевич</Description>
			<Страна>Россия</Страна>
			<Город>Саранск</Город>
			<Улица>Строительная</Улица>
			<Дом>3Г</Дом>
			<Квартира/>
			<Телефон>7991991991</Телефон>
			<ЭлектроннаяПочта/>
			<Широта>0</Широта>
			<Долгота>0</Долгота>
		</CatalogObject.Клиенты>
		<CatalogObject.Клиенты>
			<Ref>9b2782cd-5b90-11ed-9bff-841c095bda83</Ref>
			<DeletionMark>false</DeletionMark>
			<Code>000000002</Code>
			<Description>Человечный Человек Человекович</Description>
			<Страна>Россия</Страна>
			<Город>Саранск</Город>
			<Улица>Советская</Улица>
			<Дом>26</Дом>
			<Квартира>23</Квартира>
			<Телефон/>
			<ЭлектроннаяПочта/>
			<Широта>0</Широта>
			<Долгота>0</Долгота>
		</CatalogObject.Клиенты>
		<CatalogObject.Клиенты>
			<Ref>9b2782ce-5b90-11ed-9bff-841c095bda83</Ref>
			<DeletionMark>false</DeletionMark>
			<Code>000000003</Code>
			<Description>Оптоволоконный Кабель Каналови</Description>
			<Страна>Россия</Страна>
			<Город>Саранск</Город>
			<Улица>Титова</Улица>
			<Дом>54</Дом>
			<Квартира>1</Квартира>
			<Телефон/>
			<ЭлектроннаяПочта/>
			<Широта>0</Широта>
			<Долгота>0</Долгота>
		</CatalogObject.Клиенты>
		<InformationRegisterRecordSet.ЦеныТоваров>
			<Filter>
				<Period>2022-11-03T00:00:00</Period>
				<Товар>9b2782c6-5b90-11ed-9bff-841c095bda83</Товар>
			</Filter>
			<Records>
				<Record>
					<Period>2022-11-03T00:00:00</Period>
					<Товар>9b2782c6-5b90-11ed-9bff-841c095bda83</Товар>
					<Цена>15</Цена>
				</Record>
			</Records>
		</InformationRegisterRecordSet.ЦеныТоваров>
		<InformationRegisterRecordSet.ЦеныТоваров>
			<Filter>
				<Period>2022-11-03T00:00:00</Period>
				<Товар>9b2782c7-5b90-11ed-9bff-841c095bda83</Товар>
			</Filter>
			<Records>
				<Record>
					<Period>2022-11-03T00:00:00</Period>
					<Товар>9b2782c7-5b90-11ed-9bff-841c095bda83</Товар>
					<Цена>50</Цена>
				</Record>
			</Records>
		</InformationRegisterRecordSet.ЦеныТоваров>
		<InformationRegisterRecordSet.ЦеныТоваров>
			<Filter>
				<Period>2022-11-03T00:00:00</Period>
				<Товар>9b2782c8-5b90-11ed-9bff-841c095bda83</Товар>
			</Filter>
			<Records>
				<Record>
					<Period>2022-11-03T00:00:00</Period>
					<Товар>9b2782c8-5b90-11ed-9bff-841c095bda83</Товар>
					<Цена>36</Цена>
				</Record>
			</Records>
		</InformationRegisterRecordSet.ЦеныТоваров>
		<InformationRegisterRecordSet.ЦеныТоваров>
			<Filter>
				<Period>2022-11-03T00:00:00</Period>
				<Товар>9b2782c9-5b90-11ed-9bff-841c095bda83</Товар>
			</Filter>
			<Records>
				<Record>
					<Period>2022-11-03T00:00:00</Period>
					<Товар>9b2782c9-5b90-11ed-9bff-841c095bda83</Товар>
					<Цена>45</Цена>
				</Record>
			</Records>
		</InformationRegisterRecordSet.ЦеныТоваров>
		<InformationRegisterRecordSet.ЦеныТоваров>
			<Filter>
				<Period>2022-11-03T00:00:00</Period>
				<Товар>9b2782ca-5b90-11ed-9bff-841c095bda83</Товар>
			</Filter>
			<Records>
				<Record>
					<Period>2022-11-03T00:00:00</Period>
					<Товар>9b2782ca-5b90-11ed-9bff-841c095bda83</Товар>
					<Цена>25</Цена>
				</Record>
			</Records>
		</InformationRegisterRecordSet.ЦеныТоваров>
		<InformationRegisterRecordSet.ЦеныТоваров>
			<Filter>
				<Period>2022-11-03T00:00:00</Period>
				<Товар>9b2782cb-5b90-11ed-9bff-841c095bda83</Товар>
			</Filter>
			<Records>
				<Record>
					<Period>2022-11-03T00:00:00</Period>
					<Товар>9b2782cb-5b90-11ed-9bff-841c095bda83</Товар>
					<Цена>24</Цена>
				</Record>
			</Records>
		</InformationRegisterRecordSet.ЦеныТоваров>
		<CatalogObject.Склады>
			<Ref>9b2782cf-5b90-11ed-9bff-841c095bda83</Ref>
			<DeletionMark>false</DeletionMark>
			<Code>000000001</Code>
			<Description>Склад №1</Description>
		</CatalogObject.Склады>
		<CatalogObject.Цвета>
			<Ref>9b2782d0-5b90-11ed-9bff-841c095bda83</Ref>
			<DeletionMark>false</DeletionMark>
			<Code>000000001</Code>
			<Description>Красный</Description>
		</CatalogObject.Цвета>
		<CatalogObject.Цвета>
			<Ref>9b2782d1-5b90-11ed-9bff-841c095bda83</Ref>
			<DeletionMark>false</DeletionMark>
			<Code>000000002</Code>
			<Description>Зеленый</Description>
		</CatalogObject.Цвета>
		<CatalogObject.Цвета>
			<Ref>9b2782d2-5b90-11ed-9bff-841c095bda83</Ref>
			<DeletionMark>false</DeletionMark>
			<Code>000000003</Code>
			<Description>Синий</Description>
		</CatalogObject.Цвета>
		<CatalogObject.Цвета>
			<Ref>9b2782d3-5b90-11ed-9bff-841c095bda83</Ref>
			<DeletionMark>false</DeletionMark>
			<Code>000000004</Code>
			<Description>Фиолетовыый</Description>
		</CatalogObject.Цвета>
		<CatalogObject.Цвета>
			<Ref>9b2782d4-5b90-11ed-9bff-841c095bda83</Ref>
			<DeletionMark>false</DeletionMark>
			<Code>000000005</Code>
			<Description>Желтый</Description>
		</CatalogObject.Цвета>
		<CatalogObject.Цвета>
			<Ref>9b2782dc-5b90-11ed-9bff-841c095bda83</Ref>
			<DeletionMark>false</DeletionMark>
			<Code>000000006</Code>
			<Description>Оранжевый</Description>
		</CatalogObject.Цвета>
		<CatalogObject.Размеры>
			<Ref>9b2782d5-5b90-11ed-9bff-841c095bda83</Ref>
			<DeletionMark>false</DeletionMark>
			<Code>000000001</Code>
			<Description>1х1</Description>
		</CatalogObject.Размеры>
		<CatalogObject.Размеры>
			<Ref>9b2782d6-5b90-11ed-9bff-841c095bda83</Ref>
			<DeletionMark>false</DeletionMark>
			<Code>000000002</Code>
			<Description>2х2</Description>
		</CatalogObject.Размеры>
		<CatalogObject.Пользователи>
			<Ref>9b2782d8-5b90-11ed-9bff-841c095bda83</Ref>
			<DeletionMark>false</DeletionMark>
			<Code>00000000000000000001</Code>
			<Description>Курьер 1</Description>
		</CatalogObject.Пользователи>
		<ObjectDeletion xmlns="http://v8.1c.ru/data">
			<d4p1:Ref xmlns="" xmlns:d4p1="http://v8.1c.ru/data" xmlns:xsi="http://www.w3.org/2001/XMLSchema-instance" xsi:type="CatalogRef.Пользователи">9b2782d9-5b90-11ed-9bff-841c095bda83</d4p1:Ref>
		</ObjectDeletion>
		<ObjectDeletion xmlns="http://v8.1c.ru/data">
			<d4p1:Ref xmlns="" xmlns:d4p1="http://v8.1c.ru/data" xmlns:xsi="http://www.w3.org/2001/XMLSchema-instance" xsi:type="CatalogRef.Пользователи">9b2782da-5b90-11ed-9bff-841c095bda83</d4p1:Ref>
		</ObjectDeletion>
		<CatalogObject.ПричиныОтказа>
			<Ref>9b2782d7-5b90-11ed-9bff-841c095bda83</Ref>
			<DeletionMark>false</DeletionMark>
			<Code>000000001</Code>
			<Description>Опоздание курьера</Description>
		</CatalogObject.ПричиныОтказа>
		<ObjectDeletion xmlns="http://v8.1c.ru/data">
			<d4p1:Ref xmlns="" xmlns:d4p1="http://v8.1c.ru/data" xmlns:xsi="http://www.w3.org/2001/XMLSchema-instance" xsi:type="DocumentRef.Заказ">9b2782db-5b90-11ed-9bff-841c095bda83</d4p1:Ref>
		</ObjectDeletion>
		<ObjectDeletion xmlns="http://v8.1c.ru/data">
			<d4p1:Ref xmlns="" xmlns:d4p1="http://v8.1c.ru/data" xmlns:xsi="http://www.w3.org/2001/XMLSchema-instance" xsi:type="DocumentRef.Заказ">9b2782dd-5b90-11ed-9bff-841c095bda83</d4p1:Ref>
		</ObjectDeletion>
		<DocumentObject.Заказ>
			<Ref>900cdd74-5def-11ed-9c01-f01607f9f2d8</Ref>
			<DeletionMark>false</DeletionMark>
			<Date>2022-11-06T19:27:39</Date>
			<Number>ЦО-000001</Number>
			<Posted>true</Posted>
			<Клиент>9b2782ce-5b90-11ed-9bff-841c095bda83</Клиент>
			<Курьер>9b2782d8-5b90-11ed-9bff-841c095bda83</Курьер>
			<Склад>9b2782cf-5b90-11ed-9bff-841c095bda83</Склад>
			<ДатаДоставки>2022-11-06T00:00:00</ДатаДоставки>
			<АдресДоставки>094507, Ленинградская область, город Кашира, наб. Бухарестская, 06</АдресДоставки>
			<ДополнительнаяИнформация/>
			<СтатусЗаказа>Открыт</СтатусЗаказа>
			<Товары>
				<Row>
					<Товар>9b2782ca-5b90-11ed-9bff-841c095bda83</Товар>
					<Цвет>9b2782d1-5b90-11ed-9bff-841c095bda83</Цвет>
					<Размер>9b2782d6-5b90-11ed-9bff-841c095bda83</Размер>
					<Цена>25</Цена>
					<Количество>3</Количество>
					<Сумма>75</Сумма>
					<Отказ>false</Отказ>
					<ПричинаОтказа>00000000-0000-0000-0000-000000000000</ПричинаОтказа>
				</Row>
			</Товары>
		</DocumentObject.Заказ>
		<ObjectDeletion xmlns="http://v8.1c.ru/data">
			<d4p1:Ref xmlns="" xmlns:d4p1="http://v8.1c.ru/data" xmlns:xsi="http://www.w3.org/2001/XMLSchema-instance" xsi:type="DocumentRef.Заказ">900cdd75-5def-11ed-9c01-f01607f9f2d8</d4p1:Ref>
		</ObjectDeletion>
	</v8msg:Body>
</v8msg:Message>